aqicn_api_client/__init__.py
aqicn_api_client/client.py
aqicn_api_client/helpers.py
aqicn_api_client-0.0.3.dist-info/DESCRIPTION.rst
aqicn_api_client-0.0.3.dist-info/METADATA
aqicn_api_client-0.0.3.dist-info/RECORD
aqicn_api_client-0.0.3.dist-info/WHEEL
aqicn_api_client-0.0.3.dist-info/metadata.json
aqicn_api_client-0.0.3.dist-info/top_level.txt
