Metadata-Version: 2.0
Name: aqicn-api-client
Version: 0.0.3
Summary: UNKNOWN
Home-page: UNKNOWN
Author: Krzysztof Bober
Author-email: krizzb@gmail.com
License: UNKNOWN
Platform: UNKNOWN
Requires-Dist: requests
